autoprototype/__init__.py
autoprototype/sklearnopt.py
autoprototype/tfkerasopt.py
autoprototype-1.2.2.dist-info/METADATA
autoprototype-1.2.2.dist-info/WHEEL
autoprototype-1.2.2.dist-info/top_level.txt
autoprototype-1.2.2.dist-info/RECORD
