Metadata-Version: 2.1
Name: autoprototype
Version: 1.2.2
Summary: This is a module for Hyper-parameter tuning and rapid prototyping
Home-page: https://github.com/Ideas2IT/auto-prototype.git
Author: Ankan Ghosh
Author-email: ankan@ideas2it.com
License: UNKNOWN
Keywords: autoprototype,auto-prototype,Hyper parameter Optimizations,Optuna
Platform: UNKNOWN
Requires-Python: >=3.6
Requires-Dist: tensorflow (==2.5.0)
Requires-Dist: optuna
